floating_point/__init__.py
floating_point/data_types.py
floating_point/float_round.cpp
floating_point/float_round_cuda.cu
floating_point/floating_point.cpython-310-x86_64-linux-gnu.so
floating_point/round.py
torch_floating_point-0.0.11.dist-info/METADATA
torch_floating_point-0.0.11.dist-info/WHEEL
torch_floating_point-0.0.11.dist-info/top_level.txt
torch_floating_point-0.0.11.dist-info/RECORD
