Metadata-Version: 2.1
Name: torch-floating-point
Version: 0.0.11
Summary: A PyTorch library for custom floating point quantization with autograd support
Home-page: https://github.com/SamirMoustafa/torch-floating-point
Author: Samir Moustafa
Author-email: Samir Moustafa <samir.moustafa.97@gmail.com>
Maintainer-email: Samir Moustafa <samir.moustafa.97@gmail.com>
Project-URL: Homepage, https://github.com/SamirMoustafa/torch-floating-point
Project-URL: Documentation, https://torch-floating-point.readthedocs.io/
Project-URL: Repository, https://github.com/SamirMoustafa/torch-floating-point
Project-URL: Bug Tracker, https://github.com/SamirMoustafa/torch-floating-point/issues
Project-URL: Source Code, https://github.com/SamirMoustafa/torch-floating-point
Keywords: pytorch,floating-point,quantization,autograd,machine-learning,deep-learning
Classifier: Development Status :: 4 - Beta
Classifier: Intended Audience :: Developers
Classifier: Intended Audience :: Science/Research
Classifier: License :: OSI Approved :: MIT License
Classifier: Operating System :: OS Independent
Classifier: Programming Language :: Python :: 3
Classifier: Programming Language :: Python :: 3.8
Classifier: Programming Language :: Python :: 3.9
Classifier: Programming Language :: Python :: 3.10
Classifier: Programming Language :: Python :: 3.11
Classifier: Programming Language :: Python :: 3.12
Classifier: Topic :: Scientific/Engineering :: Artificial Intelligence
Classifier: Topic :: Software Development :: Libraries :: Python Modules
Classifier: Framework :: Pytest
Requires-Python: >=3.8
Requires-Dist: torch>=2.4.0
Provides-Extra: dev
Requires-Dist: ruff>=0.1.0; extra == "dev"
Requires-Dist: pre-commit>=3.0.0; extra == "dev"
